buaa_open_source_22371550_test_package1/__init__.py
buaa_open_source_22371550_test_package1/scraper.py
buaa_open_source_22371550_test_package1-0.3.dist-info/METADATA
buaa_open_source_22371550_test_package1-0.3.dist-info/WHEEL
buaa_open_source_22371550_test_package1-0.3.dist-info/top_level.txt
buaa_open_source_22371550_test_package1-0.3.dist-info/RECORD
