Metadata-Version: 2.1
Name: buaa_open_source_22371550_test_package1
Version: 0.3
Summary: Package1 for web scraping
Author: lhc
Author-email: 1500518009@qq.com
Classifier: Programming Language :: Python :: 3
Classifier: License :: OSI Approved :: MIT License
Classifier: Operating System :: OS Independent
Requires-Python: >=3.6
Requires-Dist: requests
Requires-Dist: chardet
